assistorgapi/__init__.py
assistorgapi/academic_years.py
assistorgapi/agreements.py
assistorgapi/appsettings.py
assistorgapi/articulation.py
assistorgapi/institutions.py
assistorgapi/settings.py
assistorgapi/transferability.py
assistorgapi-0.2.1.dist-info/AUTHORS.rst
assistorgapi-0.2.1.dist-info/LICENSE
assistorgapi-0.2.1.dist-info/METADATA
assistorgapi-0.2.1.dist-info/WHEEL
assistorgapi-0.2.1.dist-info/top_level.txt
assistorgapi-0.2.1.dist-info/RECORD
