Metadata-Version: 2.2
Name: assistorgapi
Version: 0.2.1
Summary: Unofficial API wrapper for ASSIST.org's API.
Home-page: https://github.com/montesclarosglennbenedict/assistorgapi
Author: Glenn Benedict Montesclaros
Author-email: montesclarosglennbenedict@gmail.com
Maintainer: itwsaya
Maintainer-email: itwsaya@googlegroups.com
License: MIT license
Classifier: Development Status :: 2 - Pre-Alpha
Classifier: Intended Audience :: Developers
Classifier: License :: OSI Approved :: MIT License
Classifier: Natural Language :: English
Classifier: Programming Language :: Python :: 3
Classifier: Programming Language :: Python :: 3.6
Classifier: Programming Language :: Python :: 3.7
Classifier: Programming Language :: Python :: 3.8
Requires-Python: >=3.6
License-File: LICENSE
License-File: AUTHORS.rst
Dynamic: author
Dynamic: author-email
Dynamic: classifier
Dynamic: description
Dynamic: description-content-type
Dynamic: home-page
Dynamic: license
Dynamic: maintainer
Dynamic: maintainer-email
Dynamic: requires-python
Dynamic: summary
